pddl_prover/__init__.py
pddl_prover/examples.py
pddl_prover/logic.py
pddl_prover/tests.py
PDDL_Prover-1.0.0.dist-info/LICENSE
PDDL_Prover-1.0.0.dist-info/METADATA
PDDL_Prover-1.0.0.dist-info/WHEEL
PDDL_Prover-1.0.0.dist-info/top_level.txt
PDDL_Prover-1.0.0.dist-info/RECORD
