Metadata-Version: 2.1
Name: PDDL-Prover
Version: 1.0.0
Summary: A python prover for evaluating FOL formulas on PDDL
Author-email: Carlos Núñez Molina <ccaarlos@ugr.es>
License: MIT License
Project-URL: Homepage, https://github.com/TheAeryan/PDDL-Prover
Keywords: logic,automated planning,theorem prover,pddl
Classifier: License :: OSI Approved :: MIT License
Classifier: Programming Language :: Python
Classifier: Programming Language :: Python :: 3
License-File: LICENSE
